[
    {
        "id": "1",
        "nombre":"Pac-Man World Re-Pac",
        "categoria": "Aventura",
        "clasificacion": "E",
        "alt": "Imagen pacman",
        "Plataformas": ["Xbox", "PlayStation", "Nintendo Switch", "PC"],
        "Multijugador": "No",
        "Precio": 744,
        "descuento": 70,
        "Fecha": "30 de junio de 2018",
        "Desarrolladora" : "Now Production / Bandai Namco",
        "Sinopsis": "Remake del clásico Pac-Man World de PS1. Pac-Man debe rescatar a su familia explorando mundos en 3D llenos de enemigos, rompecabezas y plataformas.",
        "img" :"img/aventura/pacman.png",
        "trailer": "https://youtu.be/m88oPZTx7rI?si=DyrFav0ySBlY-iOC"
    },
    
    {
        "id": "2",
        "nombre":"Alice: Madness Returns",
        "categoria": "Terror",
        "clasificacion": "M",
        "alt": "Imagen Alice: Madness Returns",
        "Plataformas": ["Xbox", "PlayStation", "PC"],
        "Multijugador": "No",
        "Precio": 179,
        "descuento": 70,
        "Fecha": "17 de junio de 2011",
        "Desarrolladora" : "Spicy Horse Games",
        "Sinopsis": "Hace once años un pavoroso incendio acabó con la familia de Alicia y la dejó terriblemente trastornada. Más tarde fue internada en el Manicomio Rutledge, donde sufrió para hacer frente a sus demonios adentrándose aún más en su mundo de fantasía, el País de las Maravillas. Ahora, después de diez años, finalmente ha logrado asegurar su liberación. Pero aún carga con el gran daño psicológico de aquel trágico evento. Con su mente hecha jirones, es incapaz de enfrentarse al miedo provocado por sus extraños recuerdos, sueños y visiones. Quizás lo haga mejor en el País de las Maravillas. Siempre ha sido así. Suele viajar allí buscando lo que el mundo real no le puede proporcionar: seguridad, conocimiento y la verdad acerca del pasado. Pero durante su ausencia, el País de las Maravillas también ha sufrido lo suyo. Algo ha ido terriblemente mal y ahora una gran maldad se cierne sobre lo que antaño fuera su hermoso refugio. ¿Puede Alicia salvar al País de las Maravillas (y a ella misma) de la locura que los consume?",
        "img" :"img/terror/pacman.png",
        "trailer": "https://youtu.be/VR8wXsvUrBg?si=ScaRpRnOEcUc2gGV"
    },

    {
        "id": "3",
        "nombre":"Dead by Daylight",
        "categoria": "Terror",
        "clasificacion": "M",
        "alt": "Imagen Dead by Daylight",
        "Plataformas": ["Xbox", "PlayStation", "PC", "Nintendo Switch"],
        "Multijugador": "Sí",
        "Precio": 299.85,
        "descuento": 10,
        "Fecha": "14 de junio de 2016",
        "Desarrolladora" : "Behaviour Interactive Inc.",
        "Sinopsis": "Dead by Daylight es un juego de horror de multijugador (4 contra 1) en el que un jugador representa el rol del asesino despiadado y los 4 restantes juegan como supervivientes que intentan escapar de él para evitar ser capturados y asesinados.",
        "img" :"img/terror/pacman.png",
        "trailer": "https://youtu.be/JGhIXLO3ul8?si=Qbo3D1sFK6duT8Kp"
    },

    {
        "id": "4",
        "nombre":"R.E.P.O.",
        "categoria": "Terror",
        "clasificacion": "T",
        "alt": "Imagen R.E.P.O.",
        "Plataformas": ["PC"],
        "Multijugador": "Sí",
        "Precio": 123.99,
        "descuento": 50,
        "Fecha": "26 de febrero de 2025",
        "Desarrolladora" : "semiwork",
        "Sinopsis": "Un juego de horror en línea cooperativo para hasta 6 jugadores. Localiza objetos valiosos, completamente basados en física, y manipúlalos con cuidado mientras los recuperas y extraes para satisfacer los deseos de tu creador.",
        "img" :"img/terror/pacman.png",
        "trailer": "https://youtu.be/0ais4U7UX14?si=aRTZM716m7052csm"
    }, 

    {
        "id": "5",
        "nombre":"No, I'm not a Human",
        "categoria": "Terror",
        "clasificacion": "T",
        "alt": "Imagen No, I'm not a Human",
        "Plataformas": ["PC"],
        "Multijugador": "No",
        "Precio": 0,
        "descuento": 0,
        "Fecha": "26 de febrero de 2025",
        "Desarrolladora" : "Trioskaz",
        "Sinopsis": "ALERTA. Quédate adentro. Asegura tus puertas con llave. Cierra las cortinas. Solo los humanos pueden entrar. Elimina a todos los Visitantes. Una ansiedad horripilante sobre la paranoia del fin de los tiempos.",
        "img" :"img/terror/pacman.png",
        "trailer": "https://youtu.be/2k64-X_zNGg?si=0ns9SmT8PNOkmAzh"
    },    

    {
        "id": "6",
        "nombre":"Phasmophobia",
        "categoria": "Terror",
        "clasificacion": "M",
        "alt": "Imagen Phasmophobia",
        "Plataformas": ["PC, Xbox", "PlayStation"],
        "Multijugador": "Sí",
        "Precio": 227.99,
        "descuento": 40,
        "Fecha": "18 de septiembre de 2020",
        "Desarrolladora" : "Kinetic Games",
        "Sinopsis": "Phasmophobia es un juego de horror psicológico en línea cooperativo para 4 jugadores. La actividad paranormal está en aumento y depende de usted y su equipo usar todo el equipo de caza fantasmas a su disposición para recopilar la mayor cantidad de evidencia posible.",
        "img" :"img/terror/pacman.png",
        "trailer": "https://youtu.be/adFNARIHlOs?si=Vt7kBRR5i5-GdCA8"
    },

    {
        "id": "7",
        "nombre":"Ghost Watchers",
        "categoria": "Terror",
        "clasificacion": "M",
        "alt": "Imagen Ghost Watchers",
        "Plataformas": ["PC", "PlayStation"],
        "Multijugador": "Sí",
        "Precio": 154.99,
        "descuento": 30,
        "Fecha": "24 de julio de 2025",
        "Desarrolladora" : "Renderise",
        "Sinopsis": "Ghost Watchers es un juego de horror en línea cooperativo. Explorarás y cazarás fantasmas en casas abandonadas.",
        "img" :"img/terror/pacman.png",
        "trailer": "https://youtu.be/fwlKpXISjL4?si=ZaM5ObJoh3heBZmO"
    },

    {
        "id": "8",
        "nombre":"DOOM: The Dark Ages",
        "categoria": "Terror",
        "clasificacion": "M",
        "alt": "Imagen DOOM: The Dark Ages",
        "Plataformas": ["Xbox", "PlayStation", "PC"],
        "Multijugador": "No",
        "Precio": 1399,
        "descuento": 60,
        "Fecha": "14 de mayo de 2020",
        "Desarrolladora" : "id Software",
        "Sinopsis": "DOOM: The Dark Ages es la precuela de los aclamados DOOM (2016) y DOOM Eternal, y narra el épico y cinematográfico origen de la furia del DOOM Slayer. Los jugadores se pondrán en la piel del DOOM Slayer en una oscura y siniestra guerra medieval contra el infierno nunca antes vista.",
        "img" :"img/terror/pacman.png",
        "trailer": "https://youtu.be/4tk8lkmYGWQ?si=rkLmDlSIADVwnkmA"
    },

    {
        "id": "9",
        "nombre":"Resident Evil 4",
        "categoria": "Terror",
        "clasificacion": "M",
        "alt": "Imagen Resident Evil 4",
        "Plataformas": ["PlayStation", "PC", "Xbox"],
        "Multijugador": "No",
        "Precio": 559,
        "descuento": 50,
        "Fecha": "23 de marzo de 2023",
        "Desarrolladora" : "CAPCOM Co., Ltd.",
        "Sinopsis": "La supervivencia es solo el comienzo. A seis años del desastre biológico en Raccoon City, Leon S. Kennedy, uno de los sobrevivientes, rastreó a la hija secuestrada del presidente hasta una aldea europea aislada, donde algo terrible le ha ocurrido a los lugareños.",
        "img" :"img/aventura/pacman.png",
        "trailer": "https://youtu.be/Yj9UeZzp12o?si=Lhm24Qu1TyQ5VhKB"
    },

    {
        "id": "10",
        "nombre":"SILENT HILL 2",
        "categoria": "Terror",
        "clasificacion": "M",
        "alt": "Imagen SILENT HILL 2",
        "Plataformas": ["PlayStation", "PC"],
        "Multijugador": "No",
        "Precio": 1195,
        "descuento": 30,
        "Fecha": "7 de octubre de 2024",
        "Desarrolladora" : "Bloober Team SA",
        "Sinopsis": "Silent Hill 2 es un juego de terror psicológico en tercera persona que sigue a James Sunderland, quien llega a la misteriosa ciudad de Silent Hill después de recibir una carta de su esposa fallecida. A medida que explora la ciudad, James se enfrenta a sus propios demonios internos y a criaturas aterradoras que reflejan sus miedos y culpas.",
        "img" :"img/aventura/pacman.png",
        "trailer": "https://youtu.be/7f5qac5f3mE?si=JfEXrWfRMH82uKhc"
    },

    {
        "id": "11",
        "nombre":"Outlast",
        "categoria": "Terror",
        "clasificacion": "M",
        "alt": "Imagen Outlast",
        "Plataformas": ["PlayStation", "PC", "Xbox"],
        "Multijugador": "No",
        "Precio": 178.99,
        "descuento": 30,
        "Fecha": "4 de septiembre de 2013",
        "Desarrolladora" : "Red Barrels",
        "Sinopsis": "Outlast es un juego de terror en primera persona que sigue a un periodista de investigación llamado Miles Upshur, quien se infiltra en un asilo psiquiátrico abandonado para descubrir la verdad detrás de los experimentos inhumanos que se llevaron a cabo allí. Armado solo con una cámara de video, Miles debe evitar a los peligrosos pacientes y descubrir los oscuros secretos del asilo.",
        "img" :"img/aventura/pacman.png",
        "trailer": "https://youtu.be/uKA-IA4locM?si=J5BBqk8N42EyJdX7"
    },

    {
        "id": "12",
        "nombre":"Omori",
        "categoria": "Rol",
        "clasificacion": "T",
        "alt": "Imagen Omori",
        "Plataformas": ["PlayStation", "PC", "Xbox", "Nintendo Switch"],
        "Multijugador": "No",
        "Precio": 320,
        "descuento": 20,
        "Fecha": "10 de diciembre de 2020",
        "Desarrolladora" : "Omocat",
        "Sinopsis": "RPG emocional de pixel art: explora sueños y traumas en historias profundas.",
        "img" :"img/aventura/pacman.png",
        "trailer": "https://youtu.be/erzgjfU271g?si=n9yi-gVa8ud8Fjoq"
    },

    {
        "id": "13",
        "nombre":"Ib",
        "categoria": "Rol",
        "clasificacion": "E",
        "alt": "Imagen Ib",
        "Plataformas": ["PC", "Nintendo Switch"],
        "Multijugador": "No",
        "Precio": 150,
        "descuento": 30,
        "Fecha": "2012",
        "Desarrolladora" : "kouri",
        "Sinopsis": "Visual novel/RPG de terror artístico en una galería de arte surrealista.",
        "img" :"img/aventura/pacman.png",
        "trailer": "https://youtu.be/TTRPYLjRGjA?si=ZnbJdHD8haFmhws2"
    },

    {
        "id": "14",
        "nombre":"Undertale",
        "categoria": "Rol",
        "clasificacion": "T",
        "alt": "Imagen Undertale",
        "Plataformas": ["PC", "Nintendo Switch"],
        "Multijugador": "No",
        "Precio": 50,
        "descuento": 75,
        "Fecha": "septiembre 2015",
        "Desarrolladora" : "tobyfox",
        "Sinopsis": "RPG único donde puedes evitar matar, con impacto emocional y humor irreverente.",
        "img" :"img/aventura/pacman.png",
        "trailer": "https://youtu.be/1Hojv0m3TqA?si=FqdIj2Q1NdTCXyxy"
    },

    {
        "id": "15",
        "nombre":"Deltarune",
        "categoria": "Rol",
        "clasificacion": "T",
        "alt": "Imagen Deltarune",
        "Plataformas": ["PC", "Nintendo Switch"],
        "Multijugador": "No",
        "Precio": 400,
        "descuento": 30,
        "Fecha": "2018",
        "Desarrolladora" : "tobyfox",
        "Sinopsis": "RPG de fantasía oscura con personajes memorables y narrativa intrigante.",
        "img" :"img/aventura/pacman.png",
        "trailer": "https://youtu.be/CN4ZcGJoZac?si=w6AQqIWpFnoVMNTh"
    },

    {
        "id": "16",
        "nombre":"Hades",
        "categoria": "Rol",
        "clasificacion": "T",
        "alt": "Imagen Hades",
        "Plataformas": ["PC", "Xbox", "Nintendo Switch", "PlayStation"],
        "Multijugador": "No",
        "Precio": 1750,
        "descuento": 75,
        "Fecha": "2020",
        "Desarrolladora" : "Supergiant Games",
        "Sinopsis": "Roguelike narrativo con acción fluida, poderosas armas mitológicas y repetición divertida.",
        "img" :"img/aventura/pacman.png",
        "trailer": "https://youtu.be/91t0ha9x0AE?si=SvERJX0KpmR3gL8W"
    },

    {
        "id": "17",
        "nombre":"Transistor",
        "categoria": "Rol",
        "clasificacion": "T",
        "alt": "Imagen Transistor",
        "Plataformas": ["PC", "Xbox", "Nintendo Switch", "PlayStation"],
        "Multijugador": "No",
        "Precio": 320,
        "descuento": 70,
        "Fecha": "2014",
        "Desarrolladora" : "Supergiant Games",
        "Sinopsis": "RPG de acción con estética cyberpunk, combate táctico y narrativa encriptada.",
        "img" :"img/aventura/pacman.png",
        "trailer": "https://youtu.be/GTik6sYT_BE?si=-LOQH3TSe6s2_Hdw"
    },

    {
        "id": "18",
        "nombre":"Fallout 4",
        "categoria": "Rol",
        "clasificacion": "M",
        "alt": "Imagen Fallout 4",
        "Plataformas": ["PC", "PlayStation", "Xbox"],
        "Multijugador": "Sí",
        "Precio": 550,
        "descuento": 80,
        "Fecha": "noviembre de 2015",
        "Desarrolladora" : "Bethesda",
        "Sinopsis": "RPG post‑apocalíptico con libertad total y exploración en la Commonwealth.",
        "img" :"img/aventura/pacman.png",
        "trailer": "https://youtu.be/XW7Of3g2JME?si=y45PSxEC_8L2q-UU"
    },

    {
        "id": "19",
        "nombre":"Genshin Impact",
        "categoria": "Rol",
        "clasificacion": "T",
        "alt": "Imagen Genshin Impact",
        "Plataformas": ["PC", "PlayStation", "Xbox", "Nintendo Switch"],
        "Multijugador": "Sí",
        "Precio": 0,
        "descuento": 0,
        "Fecha": "septiembre de 2020",
        "Desarrolladora" : "miHoYo",
        "Sinopsis": "RPG de mundo abierto estilo anime, con sistema gacha, exploración y cooperación.",
        "img" :"img/aventura/pacman.png",
        "trailer": "https://youtu.be/HLUY1nICQRY?si=N5jVnLDBIrOkU4ZE"
    },

    {
        "id": "20",
        "nombre":"The Witcher 3: Wild Hunt",
        "categoria": "Rol",
        "clasificacion": "M",
        "alt": "Imagen The Witcher 3: Wild Hunt",
        "Plataformas": ["PC", "PlayStation", "Xbox", "Nintendo Switch"],
        "Multijugador": "No",
        "Precio": 700,
        "descuento": 75,
        "Fecha": "mayo de 2015",
        "Desarrolladora" : "CD Projekt Red",
        "Sinopsis": "Acompaña a Geralt en un mundo oscuro lleno de moralidad y monstruos.",
        "img" :"img/aventura/pacman.png",
        "trailer": "https://youtu.be/c0i88t0Kacs?si=MGK3OLaD9KArzp7_"
    },

    {
        "id": "21",
        "nombre":"Divinity: Original Sin 2",
        "categoria": "Rol",
        "clasificacion": "M",
        "alt": "Imagen Divinity: Original Sin 2",
        "Plataformas": ["PC", "PlayStation", "Xbox"],
        "Multijugador": "Sí",
        "Precio": 680,
        "descuento": 70,
        "Fecha": "septiembre de 2017",
        "Desarrolladora" : "Larian Studios",
        "Sinopsis": "Épico RPG táctico con libertad argumental y multijugador cooperativo.",
        "img" :"img/aventura/pacman.png",
        "trailer": "https://youtu.be/bTWTFX8qzPI?si=DpuZzp6VA_cjSs5P"
    }      
]